[
  {
    "DisplayName": "Steam",
    "ProcessName": "steam",
    "IconLocation": "",
    "Location": 2,
    "IsHidden": false
  },
  {
    "DisplayName": "Razer Synapse 3",
    "ProcessName": "Razer Synapse 3",
    "IconLocation": "",
    "Location": 0,
    "IsHidden": true
  },
  {
    "DisplayName": "@%SystemRoot%\\System32\\AudioSrv.Dll,-202",
    "ProcessName": "@%SystemRoot%\\System32\\AudioSrv.Dll,-202",
    "IconLocation": "@%SystemRoot%\\System32\\AudioSrv.Dll,-203",
    "Location": 0,
    "IsHidden": true
  },
  {
    "DisplayName": "iCloudPhotos",
    "ProcessName": "iCloudPhotos",
    "IconLocation": "",
    "Location": 0,
    "IsHidden": true
  },
  {
    "DisplayName": "Spotify",
    "ProcessName": "Spotify",
    "IconLocation": "",
    "Location": 1,
    "IsHidden": false
  },
  {
    "DisplayName": "Google Chrome",
    "ProcessName": "chrome",
    "IconLocation": "",
    "Location": 1,
    "IsHidden": false
  },
  {
    "DisplayName": "RocketLeague",
    "ProcessName": "RocketLeague",
    "IconLocation": "",
    "Location": 2,
    "IsHidden": false
  },
  {
    "DisplayName": "svchost",
    "ProcessName": "svchost",
    "IconLocation": "",
    "Location": 0,
    "IsHidden": true
  },
  {
    "DisplayName": "DiscordHookHelper64",
    "ProcessName": "DiscordHookHelper64",
    "IconLocation": "",
    "Location": 3,
    "IsHidden": false
  },
  {
    "DisplayName": "DiscordHookHelper",
    "ProcessName": "DiscordHookHelper",
    "IconLocation": "",
    "Location": 3,
    "IsHidden": false
  },
  {
    "DisplayName": "EOSOverlayRenderer-Win64-Shipping",
    "ProcessName": "EOSOverlayRenderer-Win64-Shipping",
    "IconLocation": "",
    "Location": 0,
    "IsHidden": false
  },
  {
    "DisplayName": "Discord",
    "ProcessName": "Discord",
    "IconLocation": "",
    "Location": 3,
    "IsHidden": false
  },
  {
    "DisplayName": "Discord",
    "ProcessName": "Discord",
    "IconLocation": "",
    "Location": 3,
    "IsHidden": false
  },
  {
    "DisplayName": "Cities Skylines 2",
    "ProcessName": "Cities2",
    "IconLocation": "",
    "Location": 2,
    "IsHidden": false
  },
  {
    "DisplayName": "Cities Skylines",
    "ProcessName": "Cities",
    "IconLocation": "",
    "Location": 2,
    "IsHidden": false
  },
  {
    "DisplayName": "start_protected_game",
    "ProcessName": "start_protected_game",
    "IconLocation": "",
    "Location": 0,
    "IsHidden": false
  },
  {
    "DisplayName": "NBA 2K25",
    "ProcessName": "NBA2K25",
    "IconLocation": "",
    "Location": 2,
    "IsHidden": false
  },
  {
    "DisplayName": "Fortnite",
    "ProcessName": "FortniteClient-Win64-Shipping",
    "IconLocation": "",
    "Location": 2,
    "IsHidden": false
  },
  {
    "DisplayName": "msedge",
    "ProcessName": "msedge",
    "IconLocation": "",
    "Location": 0,
    "IsHidden": false
  },
  {
    "DisplayName": "Wallpaper Engine",
    "ProcessName": "wallpaper32",
    "IconLocation": "",
    "Location": 0,
    "IsHidden": true
  }
]